knmt-0.10.0.data/scripts/knmt
knmt-0.10.0.data/scripts/knmt-debug
knmt-0.10.0.data/scripts/knmt-server
knmt-0.10.0.dist-info/DESCRIPTION.rst
knmt-0.10.0.dist-info/METADATA
knmt-0.10.0.dist-info/RECORD
knmt-0.10.0.dist-info/WHEEL
knmt-0.10.0.dist-info/metadata.json
knmt-0.10.0.dist-info/top_level.txt
nmt_chainer/__init__.py
nmt_chainer/__main__.py
nmt_chainer/_build.py
nmt_chainer/_version.py
nmt_chainer/aligned_parse_reader.py
nmt_chainer/argument_parsing_tools.py
nmt_chainer/beam_search.py
nmt_chainer/beam_search_new.py
nmt_chainer/bhtsne.py
nmt_chainer/bleu_computer.py
nmt_chainer/chainer_bug_softmax_cross_entropy.py
nmt_chainer/char_enc_dec.py
nmt_chainer/char_output.py
nmt_chainer/client.py
nmt_chainer/constant_batch_mul.py
nmt_chainer/correct_lsb.py
nmt_chainer/count_voc.py
nmt_chainer/decoder_cells.py
nmt_chainer/eval.py
nmt_chainer/eval_bleu.py
nmt_chainer/evaluation.py
nmt_chainer/expe_recap.py
nmt_chainer/extract_dict.py
nmt_chainer/faster_gru.py
nmt_chainer/graph_training.py
nmt_chainer/ieval.py
nmt_chainer/legacy_models.py
nmt_chainer/lex_dict.py
nmt_chainer/lm_char_word.py
nmt_chainer/make_data.py
nmt_chainer/make_data_generalized.py
nmt_chainer/make_data_sent_char.py
nmt_chainer/make_data_voc_to_char.py
nmt_chainer/model_converter.py
nmt_chainer/model_report.py
nmt_chainer/models.py
nmt_chainer/process_lattice.py
nmt_chainer/replace_tgt_unk.py
nmt_chainer/resegment.py
nmt_chainer/rnn_cells.py
nmt_chainer/rodi_graph.py
nmt_chainer/sentence_reverser.py
nmt_chainer/server.py
nmt_chainer/test_multigpu.py
nmt_chainer/test_split_axis.py
nmt_chainer/train.py
nmt_chainer/training.py
nmt_chainer/training_chainer.py
nmt_chainer/tsne_vis.py
nmt_chainer/utils.py
nmt_chainer/utils_command.py
nmt_chainer/versioning_tools.py
nmt_chainer/visualisation.py
nmt_chainer/voc_to_char.py
nmt_chainer/wat_post_processing_en.py
nmt_chainer/word2vec.py
nmt_chainer/additional_links/__init__.py
nmt_chainer/additional_links/layer_normalization.py
nmt_chainer/additional_links/ln_lstm.py
nmt_chainer/additional_links/scheduled_adam.py
nmt_chainer/additional_links/test_ln.py
