Metadata-Version: 2.0
Name: knmt
Version: 0.10.0
Summary: Implementation of RNNSearch and other Neural MT models in Chainer
Home-page: https://github.com/fabiencro/knmt
Author: Fabien Cromieres
Author-email: fabien.cromieres@gmail.com
License: UNKNOWN
Platform: UNKNOWN
Requires-Dist: bokeh
Requires-Dist: chainer (>=2.0.0)
Requires-Dist: numpy (>=1.10.0)
Requires-Dist: plotly
